gc_temp_tables
