Metadata-Version: 2.1
Name: gc-temp-tables
Version: 1.1.4
Summary: Python utility for creating and querying temporary tables in Google Cloud Environments.
Home-page: https://github.com/AymoneKouame/data-science-utilities
Author: Aymone Jeanne Kouame
Author-email: aymone.jk@gmail.com
License: UNKNOWN
Platform: UNKNOWN
Classifier: Programming Language :: Python :: 3
Classifier: License :: OSI Approved :: MIT License
Classifier: Operating System :: OS Independent
Requires-Python: >=3.6
